Workbook
Name startCapital: Assumptions!$B$2
Name monthlySavings: Assumptions!$B$3
Name savingsDynamic: Assumptions!$B$4
Name expReturn: Assumptions!$B$5
Name inflation: Assumptions!$B$6
Name swr: Assumptions!$B$7
Name desiredIncome: Assumptions!$B$8
Name healthMonthly: Assumptions!$B$9
Name statePension: Assumptions!$B$10
Name currentAge: Assumptions!$B$11
Name fireAge: Assumptions!$B$12
Name pensionAge: Assumptions!$B$13
Name endAge: Assumptions!$B$14
Name taxRate: Assumptions!$B$15
Name partialExemption: Assumptions!$B$16
Name saverAllowance: Assumptions!$B$17
Name basiszins: Assumptions!$B$18
Name drawReturnDed: Assumptions!$B$19
Name withdrawalTaxDrag: Assumptions!$B$20

Sheet Read me
A1: 🔥 FIRE Analysis — General Template
A3: This workbook is a general, parametric financial-independence analysis.
A4: Change ONLY the amber cells on the 'Assumptions' sheet — every other sheet recomputes automatically.
A6: Sheets:
A7: • Assumptions — all your inputs in one place (amber = editable).
A8: • Accumulation — year-by-year portfolio growth, contributions, tax drag (Vorabpauschale) and real value.
A9: • FIRE number — how much capital you need, incl. a pension-aware two-phase estimate.
A10: • Drawdown — year-by-year decumulation with inflation-scaled, pension-credited, after-tax withdrawals.
A11: • Sensitivity — required monthly savings across a range of expected returns.
A12: • Dashboard — the KPI summary at a glance.
A14: Colour key: amber = your input, blue = calculated (do not edit).
A16: Methodology: see docs/FINANCIAL_ANALYSIS_VISION.md in the repository.
... A20: All default numbers are illustrative placeholders — replace them with your own.

Sheet Assumptions
A1: Parameter | B1: Value | C1: Notes (illustrative defaults — replace with your own)
A2: Starting capital | B2: 50000 | C2: Invested capital you already have today.
A3: Monthly savings | B3: 800 | C3: Amount invested every month (before any dynamic increase).
A4: Savings dynamic (annual) | B4: 2 | C4: Yearly % increase of the savings rate (e.g. with salary).
A5: Expected return (nominal) | B5: 7 | C5: Long-run nominal return of a broad equity ETF.
A6: Inflation | B6: 2.5 | C6: Assumed long-run price inflation.
A7: Safe withdrawal rate | B7: 3.5 | C7: Sustainable withdrawal rate (Trinity-study style).
A8: Desired monthly income (today's €) | B8: 2500 | C8: Net monthly spending you want in retirement, in today's money.
A9: Health insurance (monthly) | B9: 0 | C9: Lifelong health-insurance cost in retirement (0 = ignore).
A10: State pension (monthly, net) | B10: 1200 | C10: Expected net monthly state pension (0 = none).
A11: Current age | B11: 35 | C11: Your age today.
A12: Target FIRE age | B12: 55 | C12: Age at which you stop accumulating and start drawdown.
A13: Pension start age | B13: 67 | C13: Age at which the state pension begins.
... A20: Withdrawal tax drag | B20: 5 | C20: Approx. effective tax on gross withdrawals in drawdown.

Sheet Accumulation
A1: Year | B1: Age | C1: Start balance | D1: Contributions | E1: Growth | F1: Tax (Vorabpauschale) | G1: End balance (nominal) | H1: Price index | I1: End balance (real) | J1: Cumulative contrib. | K1: Cumulative gains
A2: =1 | B2: =currentAge+1-1 | C2: =startCapital | D2: =IF((currentAge+1-1) < fireAge, monthlySavings*12*(1+savingsDynamic/100)^(1-1), 0) | E2: =IF((currentAge+1-1) < fireAge, C2*expReturn/100 + D2*expReturn/200, 0) | F2: =IF((currentAge+1-1) < fireAge, MAX(0, (MIN(E2, C2*basiszins/100)*(1-partialExemption/100)-saverAllowance)*taxRate/100), 0) | G2: =C2+D2+E2-F2 | H2: =(1+inflation/100)^1 | I2: =G2/H2 | J2: =D2 | K2: =E2
A3: =2 | B3: =currentAge+2-1 | C3: =G2 | D3: =IF((currentAge+2-1) < fireAge, monthlySavings*12*(1+savingsDynamic/100)^(2-1), 0) | E3: =IF((currentAge+2-1) < fireAge, C3*expReturn/100 + D3*expReturn/200, 0) | F3: =IF((currentAge+2-1) < fireAge, MAX(0, (MIN(E3, C3*basiszins/100)*(1-partialExemption/100)-saverAllowance)*taxRate/100), 0) | G3: =C3+D3+E3-F3 | H3: =(1+inflation/100)^2 | I3: =G3/H3 | J3: =J2+D3 | K3: =K2+E3
A4: =3 | B4: =currentAge+3-1 | C4: =G3 | D4: =IF((currentAge+3-1) < fireAge, monthlySavings*12*(1+savingsDynamic/100)^(3-1), 0) | E4: =IF((currentAge+3-1) < fireAge, C4*expReturn/100 + D4*expReturn/200, 0) | F4: =IF((currentAge+3-1) < fireAge, MAX(0, (MIN(E4, C4*basiszins/100)*(1-partialExemption/100)-saverAllowance)*taxRate/100), 0) | G4: =C4+D4+E4-F4 | H4: =(1+inflation/100)^3 | I4: =G4/H4 | J4: =J3+D4 | K4: =K3+E4
A5: =4 | B5: =currentAge+4-1 | C5: =G4 | D5: =IF((currentAge+4-1) < fireAge, monthlySavings*12*(1+savingsDynamic/100)^(4-1), 0) | E5: =IF((currentAge+4-1) < fireAge, C5*expReturn/100 + D5*expReturn/200, 0) | F5: =IF((currentAge+4-1) < fireAge, MAX(0, (MIN(E5, C5*basiszins/100)*(1-partialExemption/100)-saverAllowance)*taxRate/100), 0) | G5: =C5+D5+E5-F5 | H5: =(1+inflation/100)^4 | I5: =G5/H5 | J5: =J4+D5 | K5: =K4+E5
A6: =5 | B6: =currentAge+5-1 | C6: =G5 | D6: =IF((currentAge+5-1) < fireAge, monthlySavings*12*(1+savingsDynamic/100)^(5-1), 0) | E6: =IF((currentAge+5-1) < fireAge, C6*expReturn/100 + D6*expReturn/200, 0) | F6: =IF((currentAge+5-1) < fireAge, MAX(0, (MIN(E6, C6*basiszins/100)*(1-partialExemption/100)-saverAllowance)*taxRate/100), 0) | G6: =C6+D6+E6-F6 | H6: =(1+inflation/100)^5 | I6: =G6/H6 | J6: =J5+D6 | K6: =K5+E6
A7: =6 | B7: =currentAge+6-1 | C7: =G6 | D7: =IF((currentAge+6-1) < fireAge, monthlySavings*12*(1+savingsDynamic/100)^(6-1), 0) | E7: =IF((currentAge+6-1) < fireAge, C7*expReturn/100 + D7*expReturn/200, 0) | F7: =IF((currentAge+6-1) < fireAge, MAX(0, (MIN(E7, C7*basiszins/100)*(1-partialExemption/100)-saverAllowance)*taxRate/100), 0) | G7: =C7+D7+E7-F7 | H7: =(1+inflation/100)^6 | I7: =G7/H7 | J7: =J6+D7 | K7: =K6+E7
A8: =7 | B8: =currentAge+7-1 | C8: =G7 | D8: =IF((currentAge+7-1) < fireAge, monthlySavings*12*(1+savingsDynamic/100)^(7-1), 0) | E8: =IF((currentAge+7-1) < fireAge, C8*expReturn/100 + D8*expReturn/200, 0) | F8: =IF((currentAge+7-1) < fireAge, MAX(0, (MIN(E8, C8*basiszins/100)*(1-partialExemption/100)-saverAllowance)*taxRate/100), 0) | G8: =C8+D8+E8-F8 | H8: =(1+inflation/100)^7 | I8: =G8/H8 | J8: =J7+D8 | K8: =K7+E8
A9: =8 | B9: =currentAge+8-1 | C9: =G8 | D9: =IF((currentAge+8-1) < fireAge, monthlySavings*12*(1+savingsDynamic/100)^(8-1), 0) | E9: =IF((currentAge+8-1) < fireAge, C9*expReturn/100 + D9*expReturn/200, 0) | F9: =IF((currentAge+8-1) < fireAge, MAX(0, (MIN(E9, C9*basiszins/100)*(1-partialExemption/100)-saverAllowance)*taxRate/100), 0) | G9: =C9+D9+E9-F9 | H9: =(1+inflation/100)^8 | I9: =G9/H9 | J9: =J8+D9 | K9: =K8+E9
A10: =9 | B10: =currentAge+9-1 | C10: =G9 | D10: =IF((currentAge+9-1) < fireAge, monthlySavings*12*(1+savingsDynamic/100)^(9-1), 0) | E10: =IF((currentAge+9-1) < fireAge, C10*expReturn/100 + D10*expReturn/200, 0) | F10: =IF((currentAge+9-1) < fireAge, MAX(0, (MIN(E10, C10*basiszins/100)*(1-partialExemption/100)-saverAllowance)*taxRate/100), 0) | G10: =C10+D10+E10-F10 | H10: =(1+inflation/100)^9 | I10: =G10/H10 | J10: =J9+D10 | K10: =K9+E10
A11: =10 | B11: =currentAge+10-1 | C11: =G10 | D11: =IF((currentAge+10-1) < fireAge, monthlySavings*12*(1+savingsDynamic/100)^(10-1), 0) | E11: =IF((currentAge+10-1) < fireAge, C11*expReturn/100 + D11*expReturn/200, 0) | F11: =IF((currentAge+10-1) < fireAge, MAX(0, (MIN(E11, C11*basiszins/100)*(1-partialExemption/100)-saverAllowance)*taxRate/100), 0) | G11: =C11+D11+E11-F11 | H11: =(1+inflation/100)^10 | I11: =G11/H11 | J11: =J10+D11 | K11: =K10+E11
A12: =11 | B12: =currentAge+11-1 | C12: =G11 | D12: =IF((currentAge+11-1) < fireAge, monthlySavings*12*(1+savingsDynamic/100)^(11-1), 0) | E12: =IF((currentAge+11-1) < fireAge, C12*expReturn/100 + D12*expReturn/200, 0) | F12: =IF((currentAge+11-1) < fireAge, MAX(0, (MIN(E12, C12*basiszins/100)*(1-partialExemption/100)-saverAllowance)*taxRate/100), 0) | G12: =C12+D12+E12-F12 | H12: =(1+inflation/100)^11 | I12: =G12/H12 | J12: =J11+D12 | K12: =K11+E12
A13: =12 | B13: =currentAge+12-1 | C13: =G12 | D13: =IF((currentAge+12-1) < fireAge, monthlySavings*12*(1+savingsDynamic/100)^(12-1), 0) | E13: =IF((currentAge+12-1) < fireAge, C13*expReturn/100 + D13*expReturn/200, 0) | F13: =IF((currentAge+12-1) < fireAge, MAX(0, (MIN(E13, C13*basiszins/100)*(1-partialExemption/100)-saverAllowance)*taxRate/100), 0) | G13: =C13+D13+E13-F13 | H13: =(1+inflation/100)^12 | I13: =G13/H13 | J13: =J12+D13 | K13: =K12+E13
A14: =13 | B14: =currentAge+13-1 | C14: =G13 | D14: =IF((currentAge+13-1) < fireAge, monthlySavings*12*(1+savingsDynamic/100)^(13-1), 0) | E14: =IF((currentAge+13-1) < fireAge, C14*expReturn/100 + D14*expReturn/200, 0) | F14: =IF((currentAge+13-1) < fireAge, MAX(0, (MIN(E14, C14*basiszins/100)*(1-partialExemption/100)-saverAllowance)*taxRate/100), 0) | G14: =C14+D14+E14-F14 | H14: =(1+inflation/100)^13 | I14: =G14/H14 | J14: =J13+D14 | K14: =K13+E14
A15: =14 | B15: =currentAge+14-1 | C15: =G14 | D15: =IF((currentAge+14-1) < fireAge, monthlySavings*12*(1+savingsDynamic/100)^(14-1), 0) | E15: =IF((currentAge+14-1) < fireAge, C15*expReturn/100 + D15*expReturn/200, 0) | F15: =IF((currentAge+14-1) < fireAge, MAX(0, (MIN(E15, C15*basiszins/100)*(1-partialExemption/100)-saverAllowance)*taxRate/100), 0) | G15: =C15+D15+E15-F15 | H15: =(1+inflation/100)^14 | I15: =G15/H15 | J15: =J14+D15 | K15: =K14+E15
A16: =15 | B16: =currentAge+15-1 | C16: =G15 | D16: =IF((currentAge+15-1) < fireAge, monthlySavings*12*(1+savingsDynamic/100)^(15-1), 0) | E16: =IF((currentAge+15-1) < fireAge, C16*expReturn/100 + D16*expReturn/200, 0) | F16: =IF((currentAge+15-1) < fireAge, MAX(0, (MIN(E16, C16*basiszins/100)*(1-partialExemption/100)-saverAllowance)*taxRate/100), 0) | G16: =C16+D16+E16-F16 | H16: =(1+inflation/100)^15 | I16: =G16/H16 | J16: =J15+D16 | K16: =K15+E16
A17: =16 | B17: =currentAge+16-1 | C17: =G16 | D17: =IF((currentAge+16-1) < fireAge, monthlySavings*12*(1+savingsDynamic/100)^(16-1), 0) | E17: =IF((currentAge+16-1) < fireAge, C17*expReturn/100 + D17*expReturn/200, 0) | F17: =IF((currentAge+16-1) < fireAge, MAX(0, (MIN(E17, C17*basiszins/100)*(1-partialExemption/100)-saverAllowance)*taxRate/100), 0) | G17: =C17+D17+E17-F17 | H17: =(1+inflation/100)^16 | I17: =G17/H17 | J17: =J16+D17 | K17: =K16+E17
A18: =17 | B18: =currentAge+17-1 | C18: =G17 | D18: =IF((currentAge+17-1) < fireAge, monthlySavings*12*(1+savingsDynamic/100)^(17-1), 0) | E18: =IF((currentAge+17-1) < fireAge, C18*expReturn/100 + D18*expReturn/200, 0) | F18: =IF((currentAge+17-1) < fireAge, MAX(0, (MIN(E18, C18*basiszins/100)*(1-partialExemption/100)-saverAllowance)*taxRate/100), 0) | G18: =C18+D18+E18-F18 | H18: =(1+inflation/100)^17 | I18: =G18/H18 | J18: =J17+D18 | K18: =K17+E18
A19: =18 | B19: =currentAge+18-1 | C19: =G18 | D19: =IF((currentAge+18-1) < fireAge, monthlySavings*12*(1+savingsDynamic/100)^(18-1), 0) | E19: =IF((currentAge+18-1) < fireAge, C19*expReturn/100 + D19*expReturn/200, 0) | F19: =IF((currentAge+18-1) < fireAge, MAX(0, (MIN(E19, C19*basiszins/100)*(1-partialExemption/100)-saverAllowance)*taxRate/100), 0) | G19: =C19+D19+E19-F19 | H19: =(1+inflation/100)^18 | I19: =G19/H19 | J19: =J18+D19 | K19: =K18+E19
A20: =19 | B20: =currentAge+19-1 | C20: =G19 | D20: =IF((currentAge+19-1) < fireAge, monthlySavings*12*(1+savingsDynamic/100)^(19-1), 0) | E20: =IF((currentAge+19-1) < fireAge, C20*expReturn/100 + D20*expReturn/200, 0) | F20: =IF((currentAge+19-1) < fireAge, MAX(0, (MIN(E20, C20*basiszins/100)*(1-partialExemption/100)-saverAllowance)*taxRate/100), 0) | G20: =C20+D20+E20-F20 | H20: =(1+inflation/100)^19 | I20: =G20/H20 | J20: =J19+D20 | K20: =K19+E20
A21: =20 | B21: =currentAge+20-1 | C21: =G20 | D21: =IF((currentAge+20-1) < fireAge, monthlySavings*12*(1+savingsDynamic/100)^(20-1), 0) | E21: =IF((currentAge+20-1) < fireAge, C21*expReturn/100 + D21*expReturn/200, 0) | F21: =IF((currentAge+20-1) < fireAge, MAX(0, (MIN(E21, C21*basiszins/100)*(1-partialExemption/100)-saverAllowance)*taxRate/100), 0) | G21: =C21+D21+E21-F21 | H21: =(1+inflation/100)^20 | I21: =G21/H21 | J21: =J20+D21 | K21: =K20+E21
A22: =21 | B22: =currentAge+21-1 | C22: =G21 | D22: =IF((currentAge+21-1) < fireAge, monthlySavings*12*(1+savingsDynamic/100)^(21-1), 0) | E22: =IF((currentAge+21-1) < fireAge, C22*expReturn/100 + D22*expReturn/200, 0) | F22: =IF((currentAge+21-1) < fireAge, MAX(0, (MIN(E22, C22*basiszins/100)*(1-partialExemption/100)-saverAllowance)*taxRate/100), 0) | G22: =C22+D22+E22-F22 | H22: =(1+inflation/100)^21 | I22: =G22/H22 | J22: =J21+D22 | K22: =K21+E22
A23: =22 | B23: =currentAge+22-1 | C23: =G22 | D23: =IF((currentAge+22-1) < fireAge, monthlySavings*12*(1+savingsDynamic/100)^(22-1), 0) | E23: =IF((currentAge+22-1) < fireAge, C23*expReturn/100 + D23*expReturn/200, 0) | F23: =IF((currentAge+22-1) < fireAge, MAX(0, (MIN(E23, C23*basiszins/100)*(1-partialExemption/100)-saverAllowance)*taxRate/100), 0) | G23: =C23+D23+E23-F23 | H23: =(1+inflation/100)^22 | I23: =G23/H23 | J23: =J22+D23 | K23: =K22+E23
A24: =23 | B24: =currentAge+23-1 | C24: =G23 | D24: =IF((currentAge+23-1) < fireAge, monthlySavings*12*(1+savingsDynamic/100)^(23-1), 0) | E24: =IF((currentAge+23-1) < fireAge, C24*expReturn/100 + D24*expReturn/200, 0) | F24: =IF((currentAge+23-1) < fireAge, MAX(0, (MIN(E24, C24*basiszins/100)*(1-partialExemption/100)-saverAllowance)*taxRate/100), 0) | G24: =C24+D24+E24-F24 | H24: =(1+inflation/100)^23 | I24: =G24/H24 | J24: =J23+D24 | K24: =K23+E24
A25: =24 | B25: =currentAge+24-1 | C25: =G24 | D25: =IF((currentAge+24-1) < fireAge, monthlySavings*12*(1+savingsDynamic/100)^(24-1), 0) | E25: =IF((currentAge+24-1) < fireAge, C25*expReturn/100 + D25*expReturn/200, 0) | F25: =IF((currentAge+24-1) < fireAge, MAX(0, (MIN(E25, C25*basiszins/100)*(1-partialExemption/100)-saverAllowance)*taxRate/100), 0) | G25: =C25+D25+E25-F25 | H25: =(1+inflation/100)^24 | I25: =G25/H25 | J25: =J24+D25 | K25: =K24+E25
A26: =25 | B26: =currentAge+25-1 | C26: =G25 | D26: =IF((currentAge+25-1) < fireAge, monthlySavings*12*(1+savingsDynamic/100)^(25-1), 0) | E26: =IF((currentAge+25-1) < fireAge, C26*expReturn/100 + D26*expReturn/200, 0) | F26: =IF((currentAge+25-1) < fireAge, MAX(0, (MIN(E26, C26*basiszins/100)*(1-partialExemption/100)-saverAllowance)*taxRate/100), 0) | G26: =C26+D26+E26-F26 | H26: =(1+inflation/100)^25 | I26: =G26/H26 | J26: =J25+D26 | K26: =K25+E26
A27: =26 | B27: =currentAge+26-1 | C27: =G26 | D27: =IF((currentAge+26-1) < fireAge, monthlySavings*12*(1+savingsDynamic/100)^(26-1), 0) | E27: =IF((currentAge+26-1) < fireAge, C27*expReturn/100 + D27*expReturn/200, 0) | F27: =IF((currentAge+26-1) < fireAge, MAX(0, (MIN(E27, C27*basiszins/100)*(1-partialExemption/100)-saverAllowance)*taxRate/100), 0) | G27: =C27+D27+E27-F27 | H27: =(1+inflation/100)^26 | I27: =G27/H27 | J27: =J26+D27 | K27: =K26+E27
A28: =27 | B28: =currentAge+27-1 | C28: =G27 | D28: =IF((currentAge+27-1) < fireAge, monthlySavings*12*(1+savingsDynamic/100)^(27-1), 0) | E28: =IF((currentAge+27-1) < fireAge, C28*expReturn/100 + D28*expReturn/200, 0) | F28: =IF((currentAge+27-1) < fireAge, MAX(0, (MIN(E28, C28*basiszins/100)*(1-partialExemption/100)-saverAllowance)*taxRate/100), 0) | G28: =C28+D28+E28-F28 | H28: =(1+inflation/100)^27 | I28: =G28/H28 | J28: =J27+D28 | K28: =K27+E28
A29: =28 | B29: =currentAge+28-1 | C29: =G28 | D29: =IF((currentAge+28-1) < fireAge, monthlySavings*12*(1+savingsDynamic/100)^(28-1), 0) | E29: =IF((currentAge+28-1) < fireAge, C29*expReturn/100 + D29*expReturn/200, 0) | F29: =IF((currentAge+28-1) < fireAge, MAX(0, (MIN(E29, C29*basiszins/100)*(1-partialExemption/100)-saverAllowance)*taxRate/100), 0) | G29: =C29+D29+E29-F29 | H29: =(1+inflation/100)^28 | I29: =G29/H29 | J29: =J28+D29 | K29: =K28+E29
A30: =29 | B30: =currentAge+29-1 | C30: =G29 | D30: =IF((currentAge+29-1) < fireAge, monthlySavings*12*(1+savingsDynamic/100)^(29-1), 0) | E30: =IF((currentAge+29-1) < fireAge, C30*expReturn/100 + D30*expReturn/200, 0) | F30: =IF((currentAge+29-1) < fireAge, MAX(0, (MIN(E30, C30*basiszins/100)*(1-partialExemption/100)-saverAllowance)*taxRate/100), 0) | G30: =C30+D30+E30-F30 | H30: =(1+inflation/100)^29 | I30: =G30/H30 | J30: =J29+D30 | K30: =K29+E30
A31: =30 | B31: =currentAge+30-1 | C31: =G30 | D31: =IF((currentAge+30-1) < fireAge, monthlySavings*12*(1+savingsDynamic/100)^(30-1), 0) | E31: =IF((currentAge+30-1) < fireAge, C31*expReturn/100 + D31*expReturn/200, 0) | F31: =IF((currentAge+30-1) < fireAge, MAX(0, (MIN(E31, C31*basiszins/100)*(1-partialExemption/100)-saverAllowance)*taxRate/100), 0) | G31: =C31+D31+E31-F31 | H31: =(1+inflation/100)^30 | I31: =G31/H31 | J31: =J30+D31 | K31: =K30+E31
A32: =31 | B32: =currentAge+31-1 | C32: =G31 | D32: =IF((currentAge+31-1) < fireAge, monthlySavings*12*(1+savingsDynamic/100)^(31-1), 0) | E32: =IF((currentAge+31-1) < fireAge, C32*expReturn/100 + D32*expReturn/200, 0) | F32: =IF((currentAge+31-1) < fireAge, MAX(0, (MIN(E32, C32*basiszins/100)*(1-partialExemption/100)-saverAllowance)*taxRate/100), 0) | G32: =C32+D32+E32-F32 | H32: =(1+inflation/100)^31 | I32: =G32/H32 | J32: =J31+D32 | K32: =K31+E32
A33: =32 | B33: =currentAge+32-1 | C33: =G32 | D33: =IF((currentAge+32-1) < fireAge, monthlySavings*12*(1+savingsDynamic/100)^(32-1), 0) | E33: =IF((currentAge+32-1) < fireAge, C33*expReturn/100 + D33*expReturn/200, 0) | F33: =IF((currentAge+32-1) < fireAge, MAX(0, (MIN(E33, C33*basiszins/100)*(1-partialExemption/100)-saverAllowance)*taxRate/100), 0) | G33: =C33+D33+E33-F33 | H33: =(1+inflation/100)^32 | I33: =G33/H33 | J33: =J32+D33 | K33: =K32+E33
A34: =33 | B34: =currentAge+33-1 | C34: =G33 | D34: =IF((currentAge+33-1) < fireAge, monthlySavings*12*(1+savingsDynamic/100)^(33-1), 0) | E34: =IF((currentAge+33-1) < fireAge, C34*expReturn/100 + D34*expReturn/200, 0) | F34: =IF((currentAge+33-1) < fireAge, MAX(0, (MIN(E34, C34*basiszins/100)*(1-partialExemption/100)-saverAllowance)*taxRate/100), 0) | G34: =C34+D34+E34-F34 | H34: =(1+inflation/100)^33 | I34: =G34/H34 | J34: =J33+D34 | K34: =K33+E34
A35: =34 | B35: =currentAge+34-1 | C35: =G34 | D35: =IF((currentAge+34-1) < fireAge, monthlySavings*12*(1+savingsDynamic/100)^(34-1), 0) | E35: =IF((currentAge+34-1) < fireAge, C35*expReturn/100 + D35*expReturn/200, 0) | F35: =IF((currentAge+34-1) < fireAge, MAX(0, (MIN(E35, C35*basiszins/100)*(1-partialExemption/100)-saverAllowance)*taxRate/100), 0) | G35: =C35+D35+E35-F35 | H35: =(1+inflation/100)^34 | I35: =G35/H35 | J35: =J34+D35 | K35: =K34+E35
A36: =35 | B36: =currentAge+35-1 | C36: =G35 | D36: =IF((currentAge+35-1) < fireAge, monthlySavings*12*(1+savingsDynamic/100)^(35-1), 0) | E36: =IF((currentAge+35-1) < fireAge, C36*expReturn/100 + D36*expReturn/200, 0) | F36: =IF((currentAge+35-1) < fireAge, MAX(0, (MIN(E36, C36*basiszins/100)*(1-partialExemption/100)-saverAllowance)*taxRate/100), 0) | G36: =C36+D36+E36-F36 | H36: =(1+inflation/100)^35 | I36: =G36/H36 | J36: =J35+D36 | K36: =K35+E36
A37: =36 | B37: =currentAge+36-1 | C37: =G36 | D37: =IF((currentAge+36-1) < fireAge, monthlySavings*12*(1+savingsDynamic/100)^(36-1), 0) | E37: =IF((currentAge+36-1) < fireAge, C37*expReturn/100 + D37*expReturn/200, 0) | F37: =IF((currentAge+36-1) < fireAge, MAX(0, (MIN(E37, C37*basiszins/100)*(1-partialExemption/100)-saverAllowance)*taxRate/100), 0) | G37: =C37+D37+E37-F37 | H37: =(1+inflation/100)^36 | I37: =G37/H37 | J37: =J36+D37 | K37: =K36+E37
A38: =37 | B38: =currentAge+37-1 | C38: =G37 | D38: =IF((currentAge+37-1) < fireAge, monthlySavings*12*(1+savingsDynamic/100)^(37-1), 0) | E38: =IF((currentAge+37-1) < fireAge, C38*expReturn/100 + D38*expReturn/200, 0) | F38: =IF((currentAge+37-1) < fireAge, MAX(0, (MIN(E38, C38*basiszins/100)*(1-partialExemption/100)-saverAllowance)*taxRate/100), 0) | G38: =C38+D38+E38-F38 | H38: =(1+inflation/100)^37 | I38: =G38/H38 | J38: =J37+D38 | K38: =K37+E38
A39: =38 | B39: =currentAge+38-1 | C39: =G38 | D39: =IF((currentAge+38-1) < fireAge, monthlySavings*12*(1+savingsDynamic/100)^(38-1), 0) | E39: =IF((currentAge+38-1) < fireAge, C39*expReturn/100 + D39*expReturn/200, 0) | F39: =IF((currentAge+38-1) < fireAge, MAX(0, (MIN(E39, C39*basiszins/100)*(1-partialExemption/100)-saverAllowance)*taxRate/100), 0) | G39: =C39+D39+E39-F39 | H39: =(1+inflation/100)^38 | I39: =G39/H39 | J39: =J38+D39 | K39: =K38+E39
A40: =39 | B40: =currentAge+39-1 | C40: =G39 | D40: =IF((currentAge+39-1) < fireAge, monthlySavings*12*(1+savingsDynamic/100)^(39-1), 0) | E40: =IF((currentAge+39-1) < fireAge, C40*expReturn/100 + D40*expReturn/200, 0) | F40: =IF((currentAge+39-1) < fireAge, MAX(0, (MIN(E40, C40*basiszins/100)*(1-partialExemption/100)-saverAllowance)*taxRate/100), 0) | G40: =C40+D40+E40-F40 | H40: =(1+inflation/100)^39 | I40: =G40/H40 | J40: =J39+D40 | K40: =K39+E40
A41: =40 | B41: =currentAge+40-1 | C41: =G40 | D41: =IF((currentAge+40-1) < fireAge, monthlySavings*12*(1+savingsDynamic/100)^(40-1), 0) | E41: =IF((currentAge+40-1) < fireAge, C41*expReturn/100 + D41*expReturn/200, 0) | F41: =IF((currentAge+40-1) < fireAge, MAX(0, (MIN(E41, C41*basiszins/100)*(1-partialExemption/100)-saverAllowance)*taxRate/100), 0) | G41: =C41+D41+E41-F41 | H41: =(1+inflation/100)^40 | I41: =G41/H41 | J41: =J40+D41 | K41: =K40+E41
A42: =41 | B42: =currentAge+41-1 | C42: =G41 | D42: =IF((currentAge+41-1) < fireAge, monthlySavings*12*(1+savingsDynamic/100)^(41-1), 0) | E42: =IF((currentAge+41-1) < fireAge, C42*expReturn/100 + D42*expReturn/200, 0) | F42: =IF((currentAge+41-1) < fireAge, MAX(0, (MIN(E42, C42*basiszins/100)*(1-partialExemption/100)-saverAllowance)*taxRate/100), 0) | G42: =C42+D42+E42-F42 | H42: =(1+inflation/100)^41 | I42: =G42/H42 | J42: =J41+D42 | K42: =K41+E42
A43: =42 | B43: =currentAge+42-1 | C43: =G42 | D43: =IF((currentAge+42-1) < fireAge, monthlySavings*12*(1+savingsDynamic/100)^(42-1), 0) | E43: =IF((currentAge+42-1) < fireAge, C43*expReturn/100 + D43*expReturn/200, 0) | F43: =IF((currentAge+42-1) < fireAge, MAX(0, (MIN(E43, C43*basiszins/100)*(1-partialExemption/100)-saverAllowance)*taxRate/100), 0) | G43: =C43+D43+E43-F43 | H43: =(1+inflation/100)^42 | I43: =G43/H43 | J43: =J42+D43 | K43: =K42+E43
A44: =43 | B44: =currentAge+43-1 | C44: =G43 | D44: =IF((currentAge+43-1) < fireAge, monthlySavings*12*(1+savingsDynamic/100)^(43-1), 0) | E44: =IF((currentAge+43-1) < fireAge, C44*expReturn/100 + D44*expReturn/200, 0) | F44: =IF((currentAge+43-1) < fireAge, MAX(0, (MIN(E44, C44*basiszins/100)*(1-partialExemption/100)-saverAllowance)*taxRate/100), 0) | G44: =C44+D44+E44-F44 | H44: =(1+inflation/100)^43 | I44: =G44/H44 | J44: =J43+D44 | K44: =K43+E44
A45: =44 | B45: =currentAge+44-1 | C45: =G44 | D45: =IF((currentAge+44-1) < fireAge, monthlySavings*12*(1+savingsDynamic/100)^(44-1), 0) | E45: =IF((currentAge+44-1) < fireAge, C45*expReturn/100 + D45*expReturn/200, 0) | F45: =IF((currentAge+44-1) < fireAge, MAX(0, (MIN(E45, C45*basiszins/100)*(1-partialExemption/100)-saverAllowance)*taxRate/100), 0) | G45: =C45+D45+E45-F45 | H45: =(1+inflation/100)^44 | I45: =G45/H45 | J45: =J44+D45 | K45: =K44+E45
A46: =45 | B46: =currentAge+45-1 | C46: =G45 | D46: =IF((currentAge+45-1) < fireAge, monthlySavings*12*(1+savingsDynamic/100)^(45-1), 0) | E46: =IF((currentAge+45-1) < fireAge, C46*expReturn/100 + D46*expReturn/200, 0) | F46: =IF((currentAge+45-1) < fireAge, MAX(0, (MIN(E46, C46*basiszins/100)*(1-partialExemption/100)-saverAllowance)*taxRate/100), 0) | G46: =C46+D46+E46-F46 | H46: =(1+inflation/100)^45 | I46: =G46/H46 | J46: =J45+D46 | K46: =K45+E46
A47: =46 | B47: =currentAge+46-1 | C47: =G46 | D47: =IF((currentAge+46-1) < fireAge, monthlySavings*12*(1+savingsDynamic/100)^(46-1), 0) | E47: =IF((currentAge+46-1) < fireAge, C47*expReturn/100 + D47*expReturn/200, 0) | F47: =IF((currentAge+46-1) < fireAge, MAX(0, (MIN(E47, C47*basiszins/100)*(1-partialExemption/100)-saverAllowance)*taxRate/100), 0) | G47: =C47+D47+E47-F47 | H47: =(1+inflation/100)^46 | I47: =G47/H47 | J47: =J46+D47 | K47: =K46+E47
A48: =47 | B48: =currentAge+47-1 | C48: =G47 | D48: =IF((currentAge+47-1) < fireAge, monthlySavings*12*(1+savingsDynamic/100)^(47-1), 0) | E48: =IF((currentAge+47-1) < fireAge, C48*expReturn/100 + D48*expReturn/200, 0) | F48: =IF((currentAge+47-1) < fireAge, MAX(0, (MIN(E48, C48*basiszins/100)*(1-partialExemption/100)-saverAllowance)*taxRate/100), 0) | G48: =C48+D48+E48-F48 | H48: =(1+inflation/100)^47 | I48: =G48/H48 | J48: =J47+D48 | K48: =K47+E48
A49: =48 | B49: =currentAge+48-1 | C49: =G48 | D49: =IF((currentAge+48-1) < fireAge, monthlySavings*12*(1+savingsDynamic/100)^(48-1), 0) | E49: =IF((currentAge+48-1) < fireAge, C49*expReturn/100 + D49*expReturn/200, 0) | F49: =IF((currentAge+48-1) < fireAge, MAX(0, (MIN(E49, C49*basiszins/100)*(1-partialExemption/100)-saverAllowance)*taxRate/100), 0) | G49: =C49+D49+E49-F49 | H49: =(1+inflation/100)^48 | I49: =G49/H49 | J49: =J48+D49 | K49: =K48+E49
A50: =49 | B50: =currentAge+49-1 | C50: =G49 | D50: =IF((currentAge+49-1) < fireAge, monthlySavings*12*(1+savingsDynamic/100)^(49-1), 0) | E50: =IF((currentAge+49-1) < fireAge, C50*expReturn/100 + D50*expReturn/200, 0) | F50: =IF((currentAge+49-1) < fireAge, MAX(0, (MIN(E50, C50*basiszins/100)*(1-partialExemption/100)-saverAllowance)*taxRate/100), 0) | G50: =C50+D50+E50-F50 | H50: =(1+inflation/100)^49 | I50: =G50/H50 | J50: =J49+D50 | K50: =K49+E50
A51: =50 | B51: =currentAge+50-1 | C51: =G50 | D51: =IF((currentAge+50-1) < fireAge, monthlySavings*12*(1+savingsDynamic/100)^(50-1), 0) | E51: =IF((currentAge+50-1) < fireAge, C51*expReturn/100 + D51*expReturn/200, 0) | F51: =IF((currentAge+50-1) < fireAge, MAX(0, (MIN(E51, C51*basiszins/100)*(1-partialExemption/100)-saverAllowance)*taxRate/100), 0) | G51: =C51+D51+E51-F51 | H51: =(1+inflation/100)^50 | I51: =G51/H51 | J51: =J50+D51 | K51: =K50+E51
A52: =51 | B52: =currentAge+51-1 | C52: =G51 | D52: =IF((currentAge+51-1) < fireAge, monthlySavings*12*(1+savingsDynamic/100)^(51-1), 0) | E52: =IF((currentAge+51-1) < fireAge, C52*expReturn/100 + D52*expReturn/200, 0) | F52: =IF((currentAge+51-1) < fireAge, MAX(0, (MIN(E52, C52*basiszins/100)*(1-partialExemption/100)-saverAllowance)*taxRate/100), 0) | G52: =C52+D52+E52-F52 | H52: =(1+inflation/100)^51 | I52: =G52/H52 | J52: =J51+D52 | K52: =K51+E52
A53: =52 | B53: =currentAge+52-1 | C53: =G52 | D53: =IF((currentAge+52-1) < fireAge, monthlySavings*12*(1+savingsDynamic/100)^(52-1), 0) | E53: =IF((currentAge+52-1) < fireAge, C53*expReturn/100 + D53*expReturn/200, 0) | F53: =IF((currentAge+52-1) < fireAge, MAX(0, (MIN(E53, C53*basiszins/100)*(1-partialExemption/100)-saverAllowance)*taxRate/100), 0) | G53: =C53+D53+E53-F53 | H53: =(1+inflation/100)^52 | I53: =G53/H53 | J53: =J52+D53 | K53: =K52+E53
A54: =53 | B54: =currentAge+53-1 | C54: =G53 | D54: =IF((currentAge+53-1) < fireAge, monthlySavings*12*(1+savingsDynamic/100)^(53-1), 0) | E54: =IF((currentAge+53-1) < fireAge, C54*expReturn/100 + D54*expReturn/200, 0) | F54: =IF((currentAge+53-1) < fireAge, MAX(0, (MIN(E54, C54*basiszins/100)*(1-partialExemption/100)-saverAllowance)*taxRate/100), 0) | G54: =C54+D54+E54-F54 | H54: =(1+inflation/100)^53 | I54: =G54/H54 | J54: =J53+D54 | K54: =K53+E54
A55: =54 | B55: =currentAge+54-1 | C55: =G54 | D55: =IF((currentAge+54-1) < fireAge, monthlySavings*12*(1+savingsDynamic/100)^(54-1), 0) | E55: =IF((currentAge+54-1) < fireAge, C55*expReturn/100 + D55*expReturn/200, 0) | F55: =IF((currentAge+54-1) < fireAge, MAX(0, (MIN(E55, C55*basiszins/100)*(1-partialExemption/100)-saverAllowance)*taxRate/100), 0) | G55: =C55+D55+E55-F55 | H55: =(1+inflation/100)^54 | I55: =G55/H55 | J55: =J54+D55 | K55: =K54+E55
A56: =55 | B56: =currentAge+55-1 | C56: =G55 | D56: =IF((currentAge+55-1) < fireAge, monthlySavings*12*(1+savingsDynamic/100)^(55-1), 0) | E56: =IF((currentAge+55-1) < fireAge, C56*expReturn/100 + D56*expReturn/200, 0) | F56: =IF((currentAge+55-1) < fireAge, MAX(0, (MIN(E56, C56*basiszins/100)*(1-partialExemption/100)-saverAllowance)*taxRate/100), 0) | G56: =C56+D56+E56-F56 | H56: =(1+inflation/100)^55 | I56: =G56/H56 | J56: =J55+D56 | K56: =K55+E56
A57: =56 | B57: =currentAge+56-1 | C57: =G56 | D57: =IF((currentAge+56-1) < fireAge, monthlySavings*12*(1+savingsDynamic/100)^(56-1), 0) | E57: =IF((currentAge+56-1) < fireAge, C57*expReturn/100 + D57*expReturn/200, 0) | F57: =IF((currentAge+56-1) < fireAge, MAX(0, (MIN(E57, C57*basiszins/100)*(1-partialExemption/100)-saverAllowance)*taxRate/100), 0) | G57: =C57+D57+E57-F57 | H57: =(1+inflation/100)^56 | I57: =G57/H57 | J57: =J56+D57 | K57: =K56+E57
A58: =57 | B58: =currentAge+57-1 | C58: =G57 | D58: =IF((currentAge+57-1) < fireAge, monthlySavings*12*(1+savingsDynamic/100)^(57-1), 0) | E58: =IF((currentAge+57-1) < fireAge, C58*expReturn/100 + D58*expReturn/200, 0) | F58: =IF((currentAge+57-1) < fireAge, MAX(0, (MIN(E58, C58*basiszins/100)*(1-partialExemption/100)-saverAllowance)*taxRate/100), 0) | G58: =C58+D58+E58-F58 | H58: =(1+inflation/100)^57 | I58: =G58/H58 | J58: =J57+D58 | K58: =K57+E58
A59: =58 | B59: =currentAge+58-1 | C59: =G58 | D59: =IF((currentAge+58-1) < fireAge, monthlySavings*12*(1+savingsDynamic/100)^(58-1), 0) | E59: =IF((currentAge+58-1) < fireAge, C59*expReturn/100 + D59*expReturn/200, 0) | F59: =IF((currentAge+58-1) < fireAge, MAX(0, (MIN(E59, C59*basiszins/100)*(1-partialExemption/100)-saverAllowance)*taxRate/100), 0) | G59: =C59+D59+E59-F59 | H59: =(1+inflation/100)^58 | I59: =G59/H59 | J59: =J58+D59 | K59: =K58+E59
A60: =59 | B60: =currentAge+59-1 | C60: =G59 | D60: =IF((currentAge+59-1) < fireAge, monthlySavings*12*(1+savingsDynamic/100)^(59-1), 0) | E60: =IF((currentAge+59-1) < fireAge, C60*expReturn/100 + D60*expReturn/200, 0) | F60: =IF((currentAge+59-1) < fireAge, MAX(0, (MIN(E60, C60*basiszins/100)*(1-partialExemption/100)-saverAllowance)*taxRate/100), 0) | G60: =C60+D60+E60-F60 | H60: =(1+inflation/100)^59 | I60: =G60/H60 | J60: =J59+D60 | K60: =K59+E60
A61: =60 | B61: =currentAge+60-1 | C61: =G60 | D61: =IF((currentAge+60-1) < fireAge, monthlySavings*12*(1+savingsDynamic/100)^(60-1), 0) | E61: =IF((currentAge+60-1) < fireAge, C61*expReturn/100 + D61*expReturn/200, 0) | F61: =IF((currentAge+60-1) < fireAge, MAX(0, (MIN(E61, C61*basiszins/100)*(1-partialExemption/100)-saverAllowance)*taxRate/100), 0) | G61: =C61+D61+E61-F61 | H61: =(1+inflation/100)^60 | I61: =G61/H61 | J61: =J60+D61 | K61: =K60+E61

Sheet FIRE number
A1: FIRE-number derivation
A2: Annual desired income (today's €) | B2: =(desiredIncome+healthMonthly)*12 | C2: Desired spend incl. health cost, per year.
A3: Annual net state pension | B3: =statePension*12 | C3: Credited once you reach pension age.
A4: Annual gap after pension | B4: =MAX(0, B2 - B3) | C4: Income still needed once the pension is paid.
A5: FIRE number — simple (income / SWR) | B5: =B2/(swr/100) | C5: Classic SWR target ignoring the pension.
A6: Capital for the post-pension gap | B6: =B4/(swr/100) | C6: SWR target for the residual gap only.
A7: Bridge years (FIRE → pension) | B7: =MAX(0, pensionAge-fireAge) | C7: Years you must fully self-fund before the pension.
A8: Bridge capital (pension pre-funding) | B8: =B3*B7 | C8: Undiscounted pension income you must bridge (conservative).
A9: FIRE number — pension-aware | B9: =B6+B8 | C9: Two-phase estimate: gap capital + bridge capital.
A10: Projected real portfolio at FIRE age | B10: =IFERROR(INDEX(Accumulation!$I:$I, MATCH(fireAge, Accumulation!$B:$B, 0)), 0) | C10: From the Accumulation sheet, today's €.
A11: Surplus / shortfall vs. pension-aware target | B11: =B10-B9 | C11: Positive = on track (real terms).

Sheet Drawdown
A1: Year | B1: Age | C1: Start balance | D1: Withdrawal need (net) | E1: Withdrawal (gross of tax) | F1: Growth | G1: End balance (nominal) | H1: End balance (real)
A2: =1 | B2: =fireAge+1-1 | C2: ='FIRE number'!B9 | D2: =IF((fireAge+1-1) <= endAge, MAX(0, (desiredIncome+healthMonthly)*12*(1+inflation/100)^((fireAge-currentAge)+1-1) - IF((fireAge+1-1)>=pensionAge, statePension*12*(1+inflation/100)^((fireAge-currentAge)+1-1), 0)), 0) | E2: =D2*(1+withdrawalTaxDrag/100) | F2: =IF((fireAge+1-1) <= endAge, MAX(0, C2-E2)*(expReturn-drawReturnDed)/100, 0) | G2: =IF((fireAge+1-1) <= endAge, MAX(0, C2-E2+F2), "") | H2: =IF((fireAge+1-1) <= endAge, G2/(1+inflation/100)^((fireAge-currentAge)+1-1+1), "")
A3: =2 | B3: =fireAge+2-1 | C3: =MAX(0, G2) | D3: =IF((fireAge+2-1) <= endAge, MAX(0, (desiredIncome+healthMonthly)*12*(1+inflation/100)^((fireAge-currentAge)+2-1) - IF((fireAge+2-1)>=pensionAge, statePension*12*(1+inflation/100)^((fireAge-currentAge)+2-1), 0)), 0) | E3: =D3*(1+withdrawalTaxDrag/100) | F3: =IF((fireAge+2-1) <= endAge, MAX(0, C3-E3)*(expReturn-drawReturnDed)/100, 0) | G3: =IF((fireAge+2-1) <= endAge, MAX(0, C3-E3+F3), "") | H3: =IF((fireAge+2-1) <= endAge, G3/(1+inflation/100)^((fireAge-currentAge)+2-1+1), "")
A4: =3 | B4: =fireAge+3-1 | C4: =MAX(0, G3) | D4: =IF((fireAge+3-1) <= endAge, MAX(0, (desiredIncome+healthMonthly)*12*(1+inflation/100)^((fireAge-currentAge)+3-1) - IF((fireAge+3-1)>=pensionAge, statePension*12*(1+inflation/100)^((fireAge-currentAge)+3-1), 0)), 0) | E4: =D4*(1+withdrawalTaxDrag/100) | F4: =IF((fireAge+3-1) <= endAge, MAX(0, C4-E4)*(expReturn-drawReturnDed)/100, 0) | G4: =IF((fireAge+3-1) <= endAge, MAX(0, C4-E4+F4), "") | H4: =IF((fireAge+3-1) <= endAge, G4/(1+inflation/100)^((fireAge-currentAge)+3-1+1), "")
A5: =4 | B5: =fireAge+4-1 | C5: =MAX(0, G4) | D5: =IF((fireAge+4-1) <= endAge, MAX(0, (desiredIncome+healthMonthly)*12*(1+inflation/100)^((fireAge-currentAge)+4-1) - IF((fireAge+4-1)>=pensionAge, statePension*12*(1+inflation/100)^((fireAge-currentAge)+4-1), 0)), 0) | E5: =D5*(1+withdrawalTaxDrag/100) | F5: =IF((fireAge+4-1) <= endAge, MAX(0, C5-E5)*(expReturn-drawReturnDed)/100, 0) | G5: =IF((fireAge+4-1) <= endAge, MAX(0, C5-E5+F5), "") | H5: =IF((fireAge+4-1) <= endAge, G5/(1+inflation/100)^((fireAge-currentAge)+4-1+1), "")
A6: =5 | B6: =fireAge+5-1 | C6: =MAX(0, G5) | D6: =IF((fireAge+5-1) <= endAge, MAX(0, (desiredIncome+healthMonthly)*12*(1+inflation/100)^((fireAge-currentAge)+5-1) - IF((fireAge+5-1)>=pensionAge, statePension*12*(1+inflation/100)^((fireAge-currentAge)+5-1), 0)), 0) | E6: =D6*(1+withdrawalTaxDrag/100) | F6: =IF((fireAge+5-1) <= endAge, MAX(0, C6-E6)*(expReturn-drawReturnDed)/100, 0) | G6: =IF((fireAge+5-1) <= endAge, MAX(0, C6-E6+F6), "") | H6: =IF((fireAge+5-1) <= endAge, G6/(1+inflation/100)^((fireAge-currentAge)+5-1+1), "")
A7: =6 | B7: =fireAge+6-1 | C7: =MAX(0, G6) | D7: =IF((fireAge+6-1) <= endAge, MAX(0, (desiredIncome+healthMonthly)*12*(1+inflation/100)^((fireAge-currentAge)+6-1) - IF((fireAge+6-1)>=pensionAge, statePension*12*(1+inflation/100)^((fireAge-currentAge)+6-1), 0)), 0) | E7: =D7*(1+withdrawalTaxDrag/100) | F7: =IF((fireAge+6-1) <= endAge, MAX(0, C7-E7)*(expReturn-drawReturnDed)/100, 0) | G7: =IF((fireAge+6-1) <= endAge, MAX(0, C7-E7+F7), "") | H7: =IF((fireAge+6-1) <= endAge, G7/(1+inflation/100)^((fireAge-currentAge)+6-1+1), "")
A8: =7 | B8: =fireAge+7-1 | C8: =MAX(0, G7) | D8: =IF((fireAge+7-1) <= endAge, MAX(0, (desiredIncome+healthMonthly)*12*(1+inflation/100)^((fireAge-currentAge)+7-1) - IF((fireAge+7-1)>=pensionAge, statePension*12*(1+inflation/100)^((fireAge-currentAge)+7-1), 0)), 0) | E8: =D8*(1+withdrawalTaxDrag/100) | F8: =IF((fireAge+7-1) <= endAge, MAX(0, C8-E8)*(expReturn-drawReturnDed)/100, 0) | G8: =IF((fireAge+7-1) <= endAge, MAX(0, C8-E8+F8), "") | H8: =IF((fireAge+7-1) <= endAge, G8/(1+inflation/100)^((fireAge-currentAge)+7-1+1), "")
A9: =8 | B9: =fireAge+8-1 | C9: =MAX(0, G8) | D9: =IF((fireAge+8-1) <= endAge, MAX(0, (desiredIncome+healthMonthly)*12*(1+inflation/100)^((fireAge-currentAge)+8-1) - IF((fireAge+8-1)>=pensionAge, statePension*12*(1+inflation/100)^((fireAge-currentAge)+8-1), 0)), 0) | E9: =D9*(1+withdrawalTaxDrag/100) | F9: =IF((fireAge+8-1) <= endAge, MAX(0, C9-E9)*(expReturn-drawReturnDed)/100, 0) | G9: =IF((fireAge+8-1) <= endAge, MAX(0, C9-E9+F9), "") | H9: =IF((fireAge+8-1) <= endAge, G9/(1+inflation/100)^((fireAge-currentAge)+8-1+1), "")
A10: =9 | B10: =fireAge+9-1 | C10: =MAX(0, G9) | D10: =IF((fireAge+9-1) <= endAge, MAX(0, (desiredIncome+healthMonthly)*12*(1+inflation/100)^((fireAge-currentAge)+9-1) - IF((fireAge+9-1)>=pensionAge, statePension*12*(1+inflation/100)^((fireAge-currentAge)+9-1), 0)), 0) | E10: =D10*(1+withdrawalTaxDrag/100) | F10: =IF((fireAge+9-1) <= endAge, MAX(0, C10-E10)*(expReturn-drawReturnDed)/100, 0) | G10: =IF((fireAge+9-1) <= endAge, MAX(0, C10-E10+F10), "") | H10: =IF((fireAge+9-1) <= endAge, G10/(1+inflation/100)^((fireAge-currentAge)+9-1+1), "")
A11: =10 | B11: =fireAge+10-1 | C11: =MAX(0, G10) | D11: =IF((fireAge+10-1) <= endAge, MAX(0, (desiredIncome+healthMonthly)*12*(1+inflation/100)^((fireAge-currentAge)+10-1) - IF((fireAge+10-1)>=pensionAge, statePension*12*(1+inflation/100)^((fireAge-currentAge)+10-1), 0)), 0) | E11: =D11*(1+withdrawalTaxDrag/100) | F11: =IF((fireAge+10-1) <= endAge, MAX(0, C11-E11)*(expReturn-drawReturnDed)/100, 0) | G11: =IF((fireAge+10-1) <= endAge, MAX(0, C11-E11+F11), "") | H11: =IF((fireAge+10-1) <= endAge, G11/(1+inflation/100)^((fireAge-currentAge)+10-1+1), "")
A12: =11 | B12: =fireAge+11-1 | C12: =MAX(0, G11) | D12: =IF((fireAge+11-1) <= endAge, MAX(0, (desiredIncome+healthMonthly)*12*(1+inflation/100)^((fireAge-currentAge)+11-1) - IF((fireAge+11-1)>=pensionAge, statePension*12*(1+inflation/100)^((fireAge-currentAge)+11-1), 0)), 0) | E12: =D12*(1+withdrawalTaxDrag/100) | F12: =IF((fireAge+11-1) <= endAge, MAX(0, C12-E12)*(expReturn-drawReturnDed)/100, 0) | G12: =IF((fireAge+11-1) <= endAge, MAX(0, C12-E12+F12), "") | H12: =IF((fireAge+11-1) <= endAge, G12/(1+inflation/100)^((fireAge-currentAge)+11-1+1), "")
A13: =12 | B13: =fireAge+12-1 | C13: =MAX(0, G12) | D13: =IF((fireAge+12-1) <= endAge, MAX(0, (desiredIncome+healthMonthly)*12*(1+inflation/100)^((fireAge-currentAge)+12-1) - IF((fireAge+12-1)>=pensionAge, statePension*12*(1+inflation/100)^((fireAge-currentAge)+12-1), 0)), 0) | E13: =D13*(1+withdrawalTaxDrag/100) | F13: =IF((fireAge+12-1) <= endAge, MAX(0, C13-E13)*(expReturn-drawReturnDed)/100, 0) | G13: =IF((fireAge+12-1) <= endAge, MAX(0, C13-E13+F13), "") | H13: =IF((fireAge+12-1) <= endAge, G13/(1+inflation/100)^((fireAge-currentAge)+12-1+1), "")
A14: =13 | B14: =fireAge+13-1 | C14: =MAX(0, G13) | D14: =IF((fireAge+13-1) <= endAge, MAX(0, (desiredIncome+healthMonthly)*12*(1+inflation/100)^((fireAge-currentAge)+13-1) - IF((fireAge+13-1)>=pensionAge, statePension*12*(1+inflation/100)^((fireAge-currentAge)+13-1), 0)), 0) | E14: =D14*(1+withdrawalTaxDrag/100) | F14: =IF((fireAge+13-1) <= endAge, MAX(0, C14-E14)*(expReturn-drawReturnDed)/100, 0) | G14: =IF((fireAge+13-1) <= endAge, MAX(0, C14-E14+F14), "") | H14: =IF((fireAge+13-1) <= endAge, G14/(1+inflation/100)^((fireAge-currentAge)+13-1+1), "")
A15: =14 | B15: =fireAge+14-1 | C15: =MAX(0, G14) | D15: =IF((fireAge+14-1) <= endAge, MAX(0, (desiredIncome+healthMonthly)*12*(1+inflation/100)^((fireAge-currentAge)+14-1) - IF((fireAge+14-1)>=pensionAge, statePension*12*(1+inflation/100)^((fireAge-currentAge)+14-1), 0)), 0) | E15: =D15*(1+withdrawalTaxDrag/100) | F15: =IF((fireAge+14-1) <= endAge, MAX(0, C15-E15)*(expReturn-drawReturnDed)/100, 0) | G15: =IF((fireAge+14-1) <= endAge, MAX(0, C15-E15+F15), "") | H15: =IF((fireAge+14-1) <= endAge, G15/(1+inflation/100)^((fireAge-currentAge)+14-1+1), "")
A16: =15 | B16: =fireAge+15-1 | C16: =MAX(0, G15) | D16: =IF((fireAge+15-1) <= endAge, MAX(0, (desiredIncome+healthMonthly)*12*(1+inflation/100)^((fireAge-currentAge)+15-1) - IF((fireAge+15-1)>=pensionAge, statePension*12*(1+inflation/100)^((fireAge-currentAge)+15-1), 0)), 0) | E16: =D16*(1+withdrawalTaxDrag/100) | F16: =IF((fireAge+15-1) <= endAge, MAX(0, C16-E16)*(expReturn-drawReturnDed)/100, 0) | G16: =IF((fireAge+15-1) <= endAge, MAX(0, C16-E16+F16), "") | H16: =IF((fireAge+15-1) <= endAge, G16/(1+inflation/100)^((fireAge-currentAge)+15-1+1), "")
A17: =16 | B17: =fireAge+16-1 | C17: =MAX(0, G16) | D17: =IF((fireAge+16-1) <= endAge, MAX(0, (desiredIncome+healthMonthly)*12*(1+inflation/100)^((fireAge-currentAge)+16-1) - IF((fireAge+16-1)>=pensionAge, statePension*12*(1+inflation/100)^((fireAge-currentAge)+16-1), 0)), 0) | E17: =D17*(1+withdrawalTaxDrag/100) | F17: =IF((fireAge+16-1) <= endAge, MAX(0, C17-E17)*(expReturn-drawReturnDed)/100, 0) | G17: =IF((fireAge+16-1) <= endAge, MAX(0, C17-E17+F17), "") | H17: =IF((fireAge+16-1) <= endAge, G17/(1+inflation/100)^((fireAge-currentAge)+16-1+1), "")
A18: =17 | B18: =fireAge+17-1 | C18: =MAX(0, G17) | D18: =IF((fireAge+17-1) <= endAge, MAX(0, (desiredIncome+healthMonthly)*12*(1+inflation/100)^((fireAge-currentAge)+17-1) - IF((fireAge+17-1)>=pensionAge, statePension*12*(1+inflation/100)^((fireAge-currentAge)+17-1), 0)), 0) | E18: =D18*(1+withdrawalTaxDrag/100) | F18: =IF((fireAge+17-1) <= endAge, MAX(0, C18-E18)*(expReturn-drawReturnDed)/100, 0) | G18: =IF((fireAge+17-1) <= endAge, MAX(0, C18-E18+F18), "") | H18: =IF((fireAge+17-1) <= endAge, G18/(1+inflation/100)^((fireAge-currentAge)+17-1+1), "")
A19: =18 | B19: =fireAge+18-1 | C19: =MAX(0, G18) | D19: =IF((fireAge+18-1) <= endAge, MAX(0, (desiredIncome+healthMonthly)*12*(1+inflation/100)^((fireAge-currentAge)+18-1) - IF((fireAge+18-1)>=pensionAge, statePension*12*(1+inflation/100)^((fireAge-currentAge)+18-1), 0)), 0) | E19: =D19*(1+withdrawalTaxDrag/100) | F19: =IF((fireAge+18-1) <= endAge, MAX(0, C19-E19)*(expReturn-drawReturnDed)/100, 0) | G19: =IF((fireAge+18-1) <= endAge, MAX(0, C19-E19+F19), "") | H19: =IF((fireAge+18-1) <= endAge, G19/(1+inflation/100)^((fireAge-currentAge)+18-1+1), "")
A20: =19 | B20: =fireAge+19-1 | C20: =MAX(0, G19) | D20: =IF((fireAge+19-1) <= endAge, MAX(0, (desiredIncome+healthMonthly)*12*(1+inflation/100)^((fireAge-currentAge)+19-1) - IF((fireAge+19-1)>=pensionAge, statePension*12*(1+inflation/100)^((fireAge-currentAge)+19-1), 0)), 0) | E20: =D20*(1+withdrawalTaxDrag/100) | F20: =IF((fireAge+19-1) <= endAge, MAX(0, C20-E20)*(expReturn-drawReturnDed)/100, 0) | G20: =IF((fireAge+19-1) <= endAge, MAX(0, C20-E20+F20), "") | H20: =IF((fireAge+19-1) <= endAge, G20/(1+inflation/100)^((fireAge-currentAge)+19-1+1), "")
A21: =20 | B21: =fireAge+20-1 | C21: =MAX(0, G20) | D21: =IF((fireAge+20-1) <= endAge, MAX(0, (desiredIncome+healthMonthly)*12*(1+inflation/100)^((fireAge-currentAge)+20-1) - IF((fireAge+20-1)>=pensionAge, statePension*12*(1+inflation/100)^((fireAge-currentAge)+20-1), 0)), 0) | E21: =D21*(1+withdrawalTaxDrag/100) | F21: =IF((fireAge+20-1) <= endAge, MAX(0, C21-E21)*(expReturn-drawReturnDed)/100, 0) | G21: =IF((fireAge+20-1) <= endAge, MAX(0, C21-E21+F21), "") | H21: =IF((fireAge+20-1) <= endAge, G21/(1+inflation/100)^((fireAge-currentAge)+20-1+1), "")
A22: =21 | B22: =fireAge+21-1 | C22: =MAX(0, G21) | D22: =IF((fireAge+21-1) <= endAge, MAX(0, (desiredIncome+healthMonthly)*12*(1+inflation/100)^((fireAge-currentAge)+21-1) - IF((fireAge+21-1)>=pensionAge, statePension*12*(1+inflation/100)^((fireAge-currentAge)+21-1), 0)), 0) | E22: =D22*(1+withdrawalTaxDrag/100) | F22: =IF((fireAge+21-1) <= endAge, MAX(0, C22-E22)*(expReturn-drawReturnDed)/100, 0) | G22: =IF((fireAge+21-1) <= endAge, MAX(0, C22-E22+F22), "") | H22: =IF((fireAge+21-1) <= endAge, G22/(1+inflation/100)^((fireAge-currentAge)+21-1+1), "")
A23: =22 | B23: =fireAge+22-1 | C23: =MAX(0, G22) | D23: =IF((fireAge+22-1) <= endAge, MAX(0, (desiredIncome+healthMonthly)*12*(1+inflation/100)^((fireAge-currentAge)+22-1) - IF((fireAge+22-1)>=pensionAge, statePension*12*(1+inflation/100)^((fireAge-currentAge)+22-1), 0)), 0) | E23: =D23*(1+withdrawalTaxDrag/100) | F23: =IF((fireAge+22-1) <= endAge, MAX(0, C23-E23)*(expReturn-drawReturnDed)/100, 0) | G23: =IF((fireAge+22-1) <= endAge, MAX(0, C23-E23+F23), "") | H23: =IF((fireAge+22-1) <= endAge, G23/(1+inflation/100)^((fireAge-currentAge)+22-1+1), "")
A24: =23 | B24: =fireAge+23-1 | C24: =MAX(0, G23) | D24: =IF((fireAge+23-1) <= endAge, MAX(0, (desiredIncome+healthMonthly)*12*(1+inflation/100)^((fireAge-currentAge)+23-1) - IF((fireAge+23-1)>=pensionAge, statePension*12*(1+inflation/100)^((fireAge-currentAge)+23-1), 0)), 0) | E24: =D24*(1+withdrawalTaxDrag/100) | F24: =IF((fireAge+23-1) <= endAge, MAX(0, C24-E24)*(expReturn-drawReturnDed)/100, 0) | G24: =IF((fireAge+23-1) <= endAge, MAX(0, C24-E24+F24), "") | H24: =IF((fireAge+23-1) <= endAge, G24/(1+inflation/100)^((fireAge-currentAge)+23-1+1), "")
A25: =24 | B25: =fireAge+24-1 | C25: =MAX(0, G24) | D25: =IF((fireAge+24-1) <= endAge, MAX(0, (desiredIncome+healthMonthly)*12*(1+inflation/100)^((fireAge-currentAge)+24-1) - IF((fireAge+24-1)>=pensionAge, statePension*12*(1+inflation/100)^((fireAge-currentAge)+24-1), 0)), 0) | E25: =D25*(1+withdrawalTaxDrag/100) | F25: =IF((fireAge+24-1) <= endAge, MAX(0, C25-E25)*(expReturn-drawReturnDed)/100, 0) | G25: =IF((fireAge+24-1) <= endAge, MAX(0, C25-E25+F25), "") | H25: =IF((fireAge+24-1) <= endAge, G25/(1+inflation/100)^((fireAge-currentAge)+24-1+1), "")
A26: =25 | B26: =fireAge+25-1 | C26: =MAX(0, G25) | D26: =IF((fireAge+25-1) <= endAge, MAX(0, (desiredIncome+healthMonthly)*12*(1+inflation/100)^((fireAge-currentAge)+25-1) - IF((fireAge+25-1)>=pensionAge, statePension*12*(1+inflation/100)^((fireAge-currentAge)+25-1), 0)), 0) | E26: =D26*(1+withdrawalTaxDrag/100) | F26: =IF((fireAge+25-1) <= endAge, MAX(0, C26-E26)*(expReturn-drawReturnDed)/100, 0) | G26: =IF((fireAge+25-1) <= endAge, MAX(0, C26-E26+F26), "") | H26: =IF((fireAge+25-1) <= endAge, G26/(1+inflation/100)^((fireAge-currentAge)+25-1+1), "")
A27: =26 | B27: =fireAge+26-1 | C27: =MAX(0, G26) | D27: =IF((fireAge+26-1) <= endAge, MAX(0, (desiredIncome+healthMonthly)*12*(1+inflation/100)^((fireAge-currentAge)+26-1) - IF((fireAge+26-1)>=pensionAge, statePension*12*(1+inflation/100)^((fireAge-currentAge)+26-1), 0)), 0) | E27: =D27*(1+withdrawalTaxDrag/100) | F27: =IF((fireAge+26-1) <= endAge, MAX(0, C27-E27)*(expReturn-drawReturnDed)/100, 0) | G27: =IF((fireAge+26-1) <= endAge, MAX(0, C27-E27+F27), "") | H27: =IF((fireAge+26-1) <= endAge, G27/(1+inflation/100)^((fireAge-currentAge)+26-1+1), "")
A28: =27 | B28: =fireAge+27-1 | C28: =MAX(0, G27) | D28: =IF((fireAge+27-1) <= endAge, MAX(0, (desiredIncome+healthMonthly)*12*(1+inflation/100)^((fireAge-currentAge)+27-1) - IF((fireAge+27-1)>=pensionAge, statePension*12*(1+inflation/100)^((fireAge-currentAge)+27-1), 0)), 0) | E28: =D28*(1+withdrawalTaxDrag/100) | F28: =IF((fireAge+27-1) <= endAge, MAX(0, C28-E28)*(expReturn-drawReturnDed)/100, 0) | G28: =IF((fireAge+27-1) <= endAge, MAX(0, C28-E28+F28), "") | H28: =IF((fireAge+27-1) <= endAge, G28/(1+inflation/100)^((fireAge-currentAge)+27-1+1), "")
A29: =28 | B29: =fireAge+28-1 | C29: =MAX(0, G28) | D29: =IF((fireAge+28-1) <= endAge, MAX(0, (desiredIncome+healthMonthly)*12*(1+inflation/100)^((fireAge-currentAge)+28-1) - IF((fireAge+28-1)>=pensionAge, statePension*12*(1+inflation/100)^((fireAge-currentAge)+28-1), 0)), 0) | E29: =D29*(1+withdrawalTaxDrag/100) | F29: =IF((fireAge+28-1) <= endAge, MAX(0, C29-E29)*(expReturn-drawReturnDed)/100, 0) | G29: =IF((fireAge+28-1) <= endAge, MAX(0, C29-E29+F29), "") | H29: =IF((fireAge+28-1) <= endAge, G29/(1+inflation/100)^((fireAge-currentAge)+28-1+1), "")
A30: =29 | B30: =fireAge+29-1 | C30: =MAX(0, G29) | D30: =IF((fireAge+29-1) <= endAge, MAX(0, (desiredIncome+healthMonthly)*12*(1+inflation/100)^((fireAge-currentAge)+29-1) - IF((fireAge+29-1)>=pensionAge, statePension*12*(1+inflation/100)^((fireAge-currentAge)+29-1), 0)), 0) | E30: =D30*(1+withdrawalTaxDrag/100) | F30: =IF((fireAge+29-1) <= endAge, MAX(0, C30-E30)*(expReturn-drawReturnDed)/100, 0) | G30: =IF((fireAge+29-1) <= endAge, MAX(0, C30-E30+F30), "") | H30: =IF((fireAge+29-1) <= endAge, G30/(1+inflation/100)^((fireAge-currentAge)+29-1+1), "")
A31: =30 | B31: =fireAge+30-1 | C31: =MAX(0, G30) | D31: =IF((fireAge+30-1) <= endAge, MAX(0, (desiredIncome+healthMonthly)*12*(1+inflation/100)^((fireAge-currentAge)+30-1) - IF((fireAge+30-1)>=pensionAge, statePension*12*(1+inflation/100)^((fireAge-currentAge)+30-1), 0)), 0) | E31: =D31*(1+withdrawalTaxDrag/100) | F31: =IF((fireAge+30-1) <= endAge, MAX(0, C31-E31)*(expReturn-drawReturnDed)/100, 0) | G31: =IF((fireAge+30-1) <= endAge, MAX(0, C31-E31+F31), "") | H31: =IF((fireAge+30-1) <= endAge, G31/(1+inflation/100)^((fireAge-currentAge)+30-1+1), "")
A32: =31 | B32: =fireAge+31-1 | C32: =MAX(0, G31) | D32: =IF((fireAge+31-1) <= endAge, MAX(0, (desiredIncome+healthMonthly)*12*(1+inflation/100)^((fireAge-currentAge)+31-1) - IF((fireAge+31-1)>=pensionAge, statePension*12*(1+inflation/100)^((fireAge-currentAge)+31-1), 0)), 0) | E32: =D32*(1+withdrawalTaxDrag/100) | F32: =IF((fireAge+31-1) <= endAge, MAX(0, C32-E32)*(expReturn-drawReturnDed)/100, 0) | G32: =IF((fireAge+31-1) <= endAge, MAX(0, C32-E32+F32), "") | H32: =IF((fireAge+31-1) <= endAge, G32/(1+inflation/100)^((fireAge-currentAge)+31-1+1), "")
A33: =32 | B33: =fireAge+32-1 | C33: =MAX(0, G32) | D33: =IF((fireAge+32-1) <= endAge, MAX(0, (desiredIncome+healthMonthly)*12*(1+inflation/100)^((fireAge-currentAge)+32-1) - IF((fireAge+32-1)>=pensionAge, statePension*12*(1+inflation/100)^((fireAge-currentAge)+32-1), 0)), 0) | E33: =D33*(1+withdrawalTaxDrag/100) | F33: =IF((fireAge+32-1) <= endAge, MAX(0, C33-E33)*(expReturn-drawReturnDed)/100, 0) | G33: =IF((fireAge+32-1) <= endAge, MAX(0, C33-E33+F33), "") | H33: =IF((fireAge+32-1) <= endAge, G33/(1+inflation/100)^((fireAge-currentAge)+32-1+1), "")
A34: =33 | B34: =fireAge+33-1 | C34: =MAX(0, G33) | D34: =IF((fireAge+33-1) <= endAge, MAX(0, (desiredIncome+healthMonthly)*12*(1+inflation/100)^((fireAge-currentAge)+33-1) - IF((fireAge+33-1)>=pensionAge, statePension*12*(1+inflation/100)^((fireAge-currentAge)+33-1), 0)), 0) | E34: =D34*(1+withdrawalTaxDrag/100) | F34: =IF((fireAge+33-1) <= endAge, MAX(0, C34-E34)*(expReturn-drawReturnDed)/100, 0) | G34: =IF((fireAge+33-1) <= endAge, MAX(0, C34-E34+F34), "") | H34: =IF((fireAge+33-1) <= endAge, G34/(1+inflation/100)^((fireAge-currentAge)+33-1+1), "")
A35: =34 | B35: =fireAge+34-1 | C35: =MAX(0, G34) | D35: =IF((fireAge+34-1) <= endAge, MAX(0, (desiredIncome+healthMonthly)*12*(1+inflation/100)^((fireAge-currentAge)+34-1) - IF((fireAge+34-1)>=pensionAge, statePension*12*(1+inflation/100)^((fireAge-currentAge)+34-1), 0)), 0) | E35: =D35*(1+withdrawalTaxDrag/100) | F35: =IF((fireAge+34-1) <= endAge, MAX(0, C35-E35)*(expReturn-drawReturnDed)/100, 0) | G35: =IF((fireAge+34-1) <= endAge, MAX(0, C35-E35+F35), "") | H35: =IF((fireAge+34-1) <= endAge, G35/(1+inflation/100)^((fireAge-currentAge)+34-1+1), "")
A36: =35 | B36: =fireAge+35-1 | C36: =MAX(0, G35) | D36: =IF((fireAge+35-1) <= endAge, MAX(0, (desiredIncome+healthMonthly)*12*(1+inflation/100)^((fireAge-currentAge)+35-1) - IF((fireAge+35-1)>=pensionAge, statePension*12*(1+inflation/100)^((fireAge-currentAge)+35-1), 0)), 0) | E36: =D36*(1+withdrawalTaxDrag/100) | F36: =IF((fireAge+35-1) <= endAge, MAX(0, C36-E36)*(expReturn-drawReturnDed)/100, 0) | G36: =IF((fireAge+35-1) <= endAge, MAX(0, C36-E36+F36), "") | H36: =IF((fireAge+35-1) <= endAge, G36/(1+inflation/100)^((fireAge-currentAge)+35-1+1), "")
A37: =36 | B37: =fireAge+36-1 | C37: =MAX(0, G36) | D37: =IF((fireAge+36-1) <= endAge, MAX(0, (desiredIncome+healthMonthly)*12*(1+inflation/100)^((fireAge-currentAge)+36-1) - IF((fireAge+36-1)>=pensionAge, statePension*12*(1+inflation/100)^((fireAge-currentAge)+36-1), 0)), 0) | E37: =D37*(1+withdrawalTaxDrag/100) | F37: =IF((fireAge+36-1) <= endAge, MAX(0, C37-E37)*(expReturn-drawReturnDed)/100, 0) | G37: =IF((fireAge+36-1) <= endAge, MAX(0, C37-E37+F37), "") | H37: =IF((fireAge+36-1) <= endAge, G37/(1+inflation/100)^((fireAge-currentAge)+36-1+1), "")
A38: =37 | B38: =fireAge+37-1 | C38: =MAX(0, G37) | D38: =IF((fireAge+37-1) <= endAge, MAX(0, (desiredIncome+healthMonthly)*12*(1+inflation/100)^((fireAge-currentAge)+37-1) - IF((fireAge+37-1)>=pensionAge, statePension*12*(1+inflation/100)^((fireAge-currentAge)+37-1), 0)), 0) | E38: =D38*(1+withdrawalTaxDrag/100) | F38: =IF((fireAge+37-1) <= endAge, MAX(0, C38-E38)*(expReturn-drawReturnDed)/100, 0) | G38: =IF((fireAge+37-1) <= endAge, MAX(0, C38-E38+F38), "") | H38: =IF((fireAge+37-1) <= endAge, G38/(1+inflation/100)^((fireAge-currentAge)+37-1+1), "")
A39: =38 | B39: =fireAge+38-1 | C39: =MAX(0, G38) | D39: =IF((fireAge+38-1) <= endAge, MAX(0, (desiredIncome+healthMonthly)*12*(1+inflation/100)^((fireAge-currentAge)+38-1) - IF((fireAge+38-1)>=pensionAge, statePension*12*(1+inflation/100)^((fireAge-currentAge)+38-1), 0)), 0) | E39: =D39*(1+withdrawalTaxDrag/100) | F39: =IF((fireAge+38-1) <= endAge, MAX(0, C39-E39)*(expReturn-drawReturnDed)/100, 0) | G39: =IF((fireAge+38-1) <= endAge, MAX(0, C39-E39+F39), "") | H39: =IF((fireAge+38-1) <= endAge, G39/(1+inflation/100)^((fireAge-currentAge)+38-1+1), "")
A40: =39 | B40: =fireAge+39-1 | C40: =MAX(0, G39) | D40: =IF((fireAge+39-1) <= endAge, MAX(0, (desiredIncome+healthMonthly)*12*(1+inflation/100)^((fireAge-currentAge)+39-1) - IF((fireAge+39-1)>=pensionAge, statePension*12*(1+inflation/100)^((fireAge-currentAge)+39-1), 0)), 0) | E40: =D40*(1+withdrawalTaxDrag/100) | F40: =IF((fireAge+39-1) <= endAge, MAX(0, C40-E40)*(expReturn-drawReturnDed)/100, 0) | G40: =IF((fireAge+39-1) <= endAge, MAX(0, C40-E40+F40), "") | H40: =IF((fireAge+39-1) <= endAge, G40/(1+inflation/100)^((fireAge-currentAge)+39-1+1), "")
A41: =40 | B41: =fireAge+40-1 | C41: =MAX(0, G40) | D41: =IF((fireAge+40-1) <= endAge, MAX(0, (desiredIncome+healthMonthly)*12*(1+inflation/100)^((fireAge-currentAge)+40-1) - IF((fireAge+40-1)>=pensionAge, statePension*12*(1+inflation/100)^((fireAge-currentAge)+40-1), 0)), 0) | E41: =D41*(1+withdrawalTaxDrag/100) | F41: =IF((fireAge+40-1) <= endAge, MAX(0, C41-E41)*(expReturn-drawReturnDed)/100, 0) | G41: =IF((fireAge+40-1) <= endAge, MAX(0, C41-E41+F41), "") | H41: =IF((fireAge+40-1) <= endAge, G41/(1+inflation/100)^((fireAge-currentAge)+40-1+1), "")
A42: =41 | B42: =fireAge+41-1 | C42: =MAX(0, G41) | D42: =IF((fireAge+41-1) <= endAge, MAX(0, (desiredIncome+healthMonthly)*12*(1+inflation/100)^((fireAge-currentAge)+41-1) - IF((fireAge+41-1)>=pensionAge, statePension*12*(1+inflation/100)^((fireAge-currentAge)+41-1), 0)), 0) | E42: =D42*(1+withdrawalTaxDrag/100) | F42: =IF((fireAge+41-1) <= endAge, MAX(0, C42-E42)*(expReturn-drawReturnDed)/100, 0) | G42: =IF((fireAge+41-1) <= endAge, MAX(0, C42-E42+F42), "") | H42: =IF((fireAge+41-1) <= endAge, G42/(1+inflation/100)^((fireAge-currentAge)+41-1+1), "")
A43: =42 | B43: =fireAge+42-1 | C43: =MAX(0, G42) | D43: =IF((fireAge+42-1) <= endAge, MAX(0, (desiredIncome+healthMonthly)*12*(1+inflation/100)^((fireAge-currentAge)+42-1) - IF((fireAge+42-1)>=pensionAge, statePension*12*(1+inflation/100)^((fireAge-currentAge)+42-1), 0)), 0) | E43: =D43*(1+withdrawalTaxDrag/100) | F43: =IF((fireAge+42-1) <= endAge, MAX(0, C43-E43)*(expReturn-drawReturnDed)/100, 0) | G43: =IF((fireAge+42-1) <= endAge, MAX(0, C43-E43+F43), "") | H43: =IF((fireAge+42-1) <= endAge, G43/(1+inflation/100)^((fireAge-currentAge)+42-1+1), "")
A44: =43 | B44: =fireAge+43-1 | C44: =MAX(0, G43) | D44: =IF((fireAge+43-1) <= endAge, MAX(0, (desiredIncome+healthMonthly)*12*(1+inflation/100)^((fireAge-currentAge)+43-1) - IF((fireAge+43-1)>=pensionAge, statePension*12*(1+inflation/100)^((fireAge-currentAge)+43-1), 0)), 0) | E44: =D44*(1+withdrawalTaxDrag/100) | F44: =IF((fireAge+43-1) <= endAge, MAX(0, C44-E44)*(expReturn-drawReturnDed)/100, 0) | G44: =IF((fireAge+43-1) <= endAge, MAX(0, C44-E44+F44), "") | H44: =IF((fireAge+43-1) <= endAge, G44/(1+inflation/100)^((fireAge-currentAge)+43-1+1), "")
A45: =44 | B45: =fireAge+44-1 | C45: =MAX(0, G44) | D45: =IF((fireAge+44-1) <= endAge, MAX(0, (desiredIncome+healthMonthly)*12*(1+inflation/100)^((fireAge-currentAge)+44-1) - IF((fireAge+44-1)>=pensionAge, statePension*12*(1+inflation/100)^((fireAge-currentAge)+44-1), 0)), 0) | E45: =D45*(1+withdrawalTaxDrag/100) | F45: =IF((fireAge+44-1) <= endAge, MAX(0, C45-E45)*(expReturn-drawReturnDed)/100, 0) | G45: =IF((fireAge+44-1) <= endAge, MAX(0, C45-E45+F45), "") | H45: =IF((fireAge+44-1) <= endAge, G45/(1+inflation/100)^((fireAge-currentAge)+44-1+1), "")
A46: =45 | B46: =fireAge+45-1 | C46: =MAX(0, G45) | D46: =IF((fireAge+45-1) <= endAge, MAX(0, (desiredIncome+healthMonthly)*12*(1+inflation/100)^((fireAge-currentAge)+45-1) - IF((fireAge+45-1)>=pensionAge, statePension*12*(1+inflation/100)^((fireAge-currentAge)+45-1), 0)), 0) | E46: =D46*(1+withdrawalTaxDrag/100) | F46: =IF((fireAge+45-1) <= endAge, MAX(0, C46-E46)*(expReturn-drawReturnDed)/100, 0) | G46: =IF((fireAge+45-1) <= endAge, MAX(0, C46-E46+F46), "") | H46: =IF((fireAge+45-1) <= endAge, G46/(1+inflation/100)^((fireAge-currentAge)+45-1+1), "")
A47: =46 | B47: =fireAge+46-1 | C47: =MAX(0, G46) | D47: =IF((fireAge+46-1) <= endAge, MAX(0, (desiredIncome+healthMonthly)*12*(1+inflation/100)^((fireAge-currentAge)+46-1) - IF((fireAge+46-1)>=pensionAge, statePension*12*(1+inflation/100)^((fireAge-currentAge)+46-1), 0)), 0) | E47: =D47*(1+withdrawalTaxDrag/100) | F47: =IF((fireAge+46-1) <= endAge, MAX(0, C47-E47)*(expReturn-drawReturnDed)/100, 0) | G47: =IF((fireAge+46-1) <= endAge, MAX(0, C47-E47+F47), "") | H47: =IF((fireAge+46-1) <= endAge, G47/(1+inflation/100)^((fireAge-currentAge)+46-1+1), "")
A48: =47 | B48: =fireAge+47-1 | C48: =MAX(0, G47) | D48: =IF((fireAge+47-1) <= endAge, MAX(0, (desiredIncome+healthMonthly)*12*(1+inflation/100)^((fireAge-currentAge)+47-1) - IF((fireAge+47-1)>=pensionAge, statePension*12*(1+inflation/100)^((fireAge-currentAge)+47-1), 0)), 0) | E48: =D48*(1+withdrawalTaxDrag/100) | F48: =IF((fireAge+47-1) <= endAge, MAX(0, C48-E48)*(expReturn-drawReturnDed)/100, 0) | G48: =IF((fireAge+47-1) <= endAge, MAX(0, C48-E48+F48), "") | H48: =IF((fireAge+47-1) <= endAge, G48/(1+inflation/100)^((fireAge-currentAge)+47-1+1), "")
A49: =48 | B49: =fireAge+48-1 | C49: =MAX(0, G48) | D49: =IF((fireAge+48-1) <= endAge, MAX(0, (desiredIncome+healthMonthly)*12*(1+inflation/100)^((fireAge-currentAge)+48-1) - IF((fireAge+48-1)>=pensionAge, statePension*12*(1+inflation/100)^((fireAge-currentAge)+48-1), 0)), 0) | E49: =D49*(1+withdrawalTaxDrag/100) | F49: =IF((fireAge+48-1) <= endAge, MAX(0, C49-E49)*(expReturn-drawReturnDed)/100, 0) | G49: =IF((fireAge+48-1) <= endAge, MAX(0, C49-E49+F49), "") | H49: =IF((fireAge+48-1) <= endAge, G49/(1+inflation/100)^((fireAge-currentAge)+48-1+1), "")
A50: =49 | B50: =fireAge+49-1 | C50: =MAX(0, G49) | D50: =IF((fireAge+49-1) <= endAge, MAX(0, (desiredIncome+healthMonthly)*12*(1+inflation/100)^((fireAge-currentAge)+49-1) - IF((fireAge+49-1)>=pensionAge, statePension*12*(1+inflation/100)^((fireAge-currentAge)+49-1), 0)), 0) | E50: =D50*(1+withdrawalTaxDrag/100) | F50: =IF((fireAge+49-1) <= endAge, MAX(0, C50-E50)*(expReturn-drawReturnDed)/100, 0) | G50: =IF((fireAge+49-1) <= endAge, MAX(0, C50-E50+F50), "") | H50: =IF((fireAge+49-1) <= endAge, G50/(1+inflation/100)^((fireAge-currentAge)+49-1+1), "")
A51: =50 | B51: =fireAge+50-1 | C51: =MAX(0, G50) | D51: =IF((fireAge+50-1) <= endAge, MAX(0, (desiredIncome+healthMonthly)*12*(1+inflation/100)^((fireAge-currentAge)+50-1) - IF((fireAge+50-1)>=pensionAge, statePension*12*(1+inflation/100)^((fireAge-currentAge)+50-1), 0)), 0) | E51: =D51*(1+withdrawalTaxDrag/100) | F51: =IF((fireAge+50-1) <= endAge, MAX(0, C51-E51)*(expReturn-drawReturnDed)/100, 0) | G51: =IF((fireAge+50-1) <= endAge, MAX(0, C51-E51+F51), "") | H51: =IF((fireAge+50-1) <= endAge, G51/(1+inflation/100)^((fireAge-currentAge)+50-1+1), "")
A52: =51 | B52: =fireAge+51-1 | C52: =MAX(0, G51) | D52: =IF((fireAge+51-1) <= endAge, MAX(0, (desiredIncome+healthMonthly)*12*(1+inflation/100)^((fireAge-currentAge)+51-1) - IF((fireAge+51-1)>=pensionAge, statePension*12*(1+inflation/100)^((fireAge-currentAge)+51-1), 0)), 0) | E52: =D52*(1+withdrawalTaxDrag/100) | F52: =IF((fireAge+51-1) <= endAge, MAX(0, C52-E52)*(expReturn-drawReturnDed)/100, 0) | G52: =IF((fireAge+51-1) <= endAge, MAX(0, C52-E52+F52), "") | H52: =IF((fireAge+51-1) <= endAge, G52/(1+inflation/100)^((fireAge-currentAge)+51-1+1), "")
A53: =52 | B53: =fireAge+52-1 | C53: =MAX(0, G52) | D53: =IF((fireAge+52-1) <= endAge, MAX(0, (desiredIncome+healthMonthly)*12*(1+inflation/100)^((fireAge-currentAge)+52-1) - IF((fireAge+52-1)>=pensionAge, statePension*12*(1+inflation/100)^((fireAge-currentAge)+52-1), 0)), 0) | E53: =D53*(1+withdrawalTaxDrag/100) | F53: =IF((fireAge+52-1) <= endAge, MAX(0, C53-E53)*(expReturn-drawReturnDed)/100, 0) | G53: =IF((fireAge+52-1) <= endAge, MAX(0, C53-E53+F53), "") | H53: =IF((fireAge+52-1) <= endAge, G53/(1+inflation/100)^((fireAge-currentAge)+52-1+1), "")
A54: =53 | B54: =fireAge+53-1 | C54: =MAX(0, G53) | D54: =IF((fireAge+53-1) <= endAge, MAX(0, (desiredIncome+healthMonthly)*12*(1+inflation/100)^((fireAge-currentAge)+53-1) - IF((fireAge+53-1)>=pensionAge, statePension*12*(1+inflation/100)^((fireAge-currentAge)+53-1), 0)), 0) | E54: =D54*(1+withdrawalTaxDrag/100) | F54: =IF((fireAge+53-1) <= endAge, MAX(0, C54-E54)*(expReturn-drawReturnDed)/100, 0) | G54: =IF((fireAge+53-1) <= endAge, MAX(0, C54-E54+F54), "") | H54: =IF((fireAge+53-1) <= endAge, G54/(1+inflation/100)^((fireAge-currentAge)+53-1+1), "")
A55: =54 | B55: =fireAge+54-1 | C55: =MAX(0, G54) | D55: =IF((fireAge+54-1) <= endAge, MAX(0, (desiredIncome+healthMonthly)*12*(1+inflation/100)^((fireAge-currentAge)+54-1) - IF((fireAge+54-1)>=pensionAge, statePension*12*(1+inflation/100)^((fireAge-currentAge)+54-1), 0)), 0) | E55: =D55*(1+withdrawalTaxDrag/100) | F55: =IF((fireAge+54-1) <= endAge, MAX(0, C55-E55)*(expReturn-drawReturnDed)/100, 0) | G55: =IF((fireAge+54-1) <= endAge, MAX(0, C55-E55+F55), "") | H55: =IF((fireAge+54-1) <= endAge, G55/(1+inflation/100)^((fireAge-currentAge)+54-1+1), "")
A56: =55 | B56: =fireAge+55-1 | C56: =MAX(0, G55) | D56: =IF((fireAge+55-1) <= endAge, MAX(0, (desiredIncome+healthMonthly)*12*(1+inflation/100)^((fireAge-currentAge)+55-1) - IF((fireAge+55-1)>=pensionAge, statePension*12*(1+inflation/100)^((fireAge-currentAge)+55-1), 0)), 0) | E56: =D56*(1+withdrawalTaxDrag/100) | F56: =IF((fireAge+55-1) <= endAge, MAX(0, C56-E56)*(expReturn-drawReturnDed)/100, 0) | G56: =IF((fireAge+55-1) <= endAge, MAX(0, C56-E56+F56), "") | H56: =IF((fireAge+55-1) <= endAge, G56/(1+inflation/100)^((fireAge-currentAge)+55-1+1), "")
A57: =56 | B57: =fireAge+56-1 | C57: =MAX(0, G56) | D57: =IF((fireAge+56-1) <= endAge, MAX(0, (desiredIncome+healthMonthly)*12*(1+inflation/100)^((fireAge-currentAge)+56-1) - IF((fireAge+56-1)>=pensionAge, statePension*12*(1+inflation/100)^((fireAge-currentAge)+56-1), 0)), 0) | E57: =D57*(1+withdrawalTaxDrag/100) | F57: =IF((fireAge+56-1) <= endAge, MAX(0, C57-E57)*(expReturn-drawReturnDed)/100, 0) | G57: =IF((fireAge+56-1) <= endAge, MAX(0, C57-E57+F57), "") | H57: =IF((fireAge+56-1) <= endAge, G57/(1+inflation/100)^((fireAge-currentAge)+56-1+1), "")
A58: =57 | B58: =fireAge+57-1 | C58: =MAX(0, G57) | D58: =IF((fireAge+57-1) <= endAge, MAX(0, (desiredIncome+healthMonthly)*12*(1+inflation/100)^((fireAge-currentAge)+57-1) - IF((fireAge+57-1)>=pensionAge, statePension*12*(1+inflation/100)^((fireAge-currentAge)+57-1), 0)), 0) | E58: =D58*(1+withdrawalTaxDrag/100) | F58: =IF((fireAge+57-1) <= endAge, MAX(0, C58-E58)*(expReturn-drawReturnDed)/100, 0) | G58: =IF((fireAge+57-1) <= endAge, MAX(0, C58-E58+F58), "") | H58: =IF((fireAge+57-1) <= endAge, G58/(1+inflation/100)^((fireAge-currentAge)+57-1+1), "")
A59: =58 | B59: =fireAge+58-1 | C59: =MAX(0, G58) | D59: =IF((fireAge+58-1) <= endAge, MAX(0, (desiredIncome+healthMonthly)*12*(1+inflation/100)^((fireAge-currentAge)+58-1) - IF((fireAge+58-1)>=pensionAge, statePension*12*(1+inflation/100)^((fireAge-currentAge)+58-1), 0)), 0) | E59: =D59*(1+withdrawalTaxDrag/100) | F59: =IF((fireAge+58-1) <= endAge, MAX(0, C59-E59)*(expReturn-drawReturnDed)/100, 0) | G59: =IF((fireAge+58-1) <= endAge, MAX(0, C59-E59+F59), "") | H59: =IF((fireAge+58-1) <= endAge, G59/(1+inflation/100)^((fireAge-currentAge)+58-1+1), "")
A60: =59 | B60: =fireAge+59-1 | C60: =MAX(0, G59) | D60: =IF((fireAge+59-1) <= endAge, MAX(0, (desiredIncome+healthMonthly)*12*(1+inflation/100)^((fireAge-currentAge)+59-1) - IF((fireAge+59-1)>=pensionAge, statePension*12*(1+inflation/100)^((fireAge-currentAge)+59-1), 0)), 0) | E60: =D60*(1+withdrawalTaxDrag/100) | F60: =IF((fireAge+59-1) <= endAge, MAX(0, C60-E60)*(expReturn-drawReturnDed)/100, 0) | G60: =IF((fireAge+59-1) <= endAge, MAX(0, C60-E60+F60), "") | H60: =IF((fireAge+59-1) <= endAge, G60/(1+inflation/100)^((fireAge-currentAge)+59-1+1), "")
A61: =60 | B61: =fireAge+60-1 | C61: =MAX(0, G60) | D61: =IF((fireAge+60-1) <= endAge, MAX(0, (desiredIncome+healthMonthly)*12*(1+inflation/100)^((fireAge-currentAge)+60-1) - IF((fireAge+60-1)>=pensionAge, statePension*12*(1+inflation/100)^((fireAge-currentAge)+60-1), 0)), 0) | E61: =D61*(1+withdrawalTaxDrag/100) | F61: =IF((fireAge+60-1) <= endAge, MAX(0, C61-E61)*(expReturn-drawReturnDed)/100, 0) | G61: =IF((fireAge+60-1) <= endAge, MAX(0, C61-E61+F61), "") | H61: =IF((fireAge+60-1) <= endAge, G61/(1+inflation/100)^((fireAge-currentAge)+60-1+1), "")

Sheet Sensitivity
A1: Expected return | B1: Required monthly savings | C1: Nominal target at FIRE age
A2: 4 | B2: =MAX(0, (C2 - startCapital*(1+4/100)^(fireAge-currentAge)) * (4/100) / (((1+4/100)^(fireAge-currentAge))-1) / 12) | C2: ='FIRE number'!B9*(1+inflation/100)^(fireAge-currentAge)
A3: 5 | B3: =MAX(0, (C3 - startCapital*(1+5/100)^(fireAge-currentAge)) * (5/100) / (((1+5/100)^(fireAge-currentAge))-1) / 12) | C3: ='FIRE number'!B9*(1+inflation/100)^(fireAge-currentAge)
A4: 6 | B4: =MAX(0, (C4 - startCapital*(1+6/100)^(fireAge-currentAge)) * (6/100) / (((1+6/100)^(fireAge-currentAge))-1) / 12) | C4: ='FIRE number'!B9*(1+inflation/100)^(fireAge-currentAge)
A5: 7 | B5: =MAX(0, (C5 - startCapital*(1+7/100)^(fireAge-currentAge)) * (7/100) / (((1+7/100)^(fireAge-currentAge))-1) / 12) | C5: ='FIRE number'!B9*(1+inflation/100)^(fireAge-currentAge)
A6: 8 | B6: =MAX(0, (C6 - startCapital*(1+8/100)^(fireAge-currentAge)) * (8/100) / (((1+8/100)^(fireAge-currentAge))-1) / 12) | C6: ='FIRE number'!B9*(1+inflation/100)^(fireAge-currentAge)
A7: 9 | B7: =MAX(0, (C7 - startCapital*(1+9/100)^(fireAge-currentAge)) * (9/100) / (((1+9/100)^(fireAge-currentAge))-1) / 12) | C7: ='FIRE number'!B9*(1+inflation/100)^(fireAge-currentAge)
A8: 10 | B8: =MAX(0, (C8 - startCapital*(1+10/100)^(fireAge-currentAge)) * (10/100) / (((1+10/100)^(fireAge-currentAge))-1) / 12) | C8: ='FIRE number'!B9*(1+inflation/100)^(fireAge-currentAge)

Sheet Dashboard
A1: KPI Dashboard
A3: FIRE number (pension-aware) | B3: ='FIRE number'!B9
A4: FIRE number (simple SWR) | B4: ='FIRE number'!B4
A5: Projected real portfolio at FIRE age | B5: ='FIRE number'!B10
A6: Surplus / shortfall (real) | B6: ='FIRE number'!B11
A7: Years to FIRE | B7: =fireAge-currentAge
A8: Desired annual income (today's €) | B8: =(desiredIncome+healthMonthly)*12
A9: Sustainable income at SWR | B9: ='FIRE number'!B9*swr/100
A10: Portfolio at end of plan (real) | B10: =INDEX(Drawdown!$H:$H, MATCH(endAge, Drawdown!$B:$B, 0))
